putdig_server/__init__.py
putdig_server/server.py
putdig_server/dist/edit.html
putdig_server/dist/index.html
putdig_server/dist/static/edit.js
putdig_server/dist/static/index.js
PuTDIG-0.0.2.dist-info/METADATA
PuTDIG-0.0.2.dist-info/WHEEL
PuTDIG-0.0.2.dist-info/entry_points.txt
PuTDIG-0.0.2.dist-info/top_level.txt
PuTDIG-0.0.2.dist-info/RECORD
