Metadata-Version: 2.1
Name: PuTDIG
Version: 0.0.2
Summary: Web-based version of the PuTDIG suite of applications to discover, inject and generate telemetry
Home-page: https://github.com/PumpkinSpace/PuTDIG
Author: James Womack, Jack Hughes
Author-email: info@pumpkininc.com
License: UNKNOWN
Platform: UNKNOWN
Classifier: Programming Language :: Python :: 3
Classifier: License :: OSI Approved :: MIT License
Classifier: Operating System :: OS Independent
Requires-Python: >=3.7
Requires-Dist: pumpkin-supmcu
Requires-Dist: putdig-common
Requires-Dist: flask
Requires-Dist: flask-wtf
Requires-Dist: waitress
